iceoryx2-0.8.1.dist-info/METADATA
iceoryx2-0.8.1.dist-info/WHEEL
iceoryx2/__init__.py
iceoryx2/_iceoryx2.abi3.so
iceoryx2/blackboard_extensions.py
iceoryx2/publish_subscribe_extensions.py
iceoryx2/request_response_extensions.py
iceoryx2/slice.py
iceoryx2/type_name.py
iceoryx2-0.8.1.dist-info/RECORD
