Metadata-Version: 2.4
Name: iceoryx2
Version: 0.8.1
Classifier: Programming Language :: Python :: 3 :: Only
Classifier: Programming Language :: Python :: 3.8
Classifier: Programming Language :: Python :: 3.9
Classifier: Programming Language :: Python :: 3.10
Classifier: Programming Language :: Python :: 3.11
Classifier: Programming Language :: Python :: 3.12
Classifier: Programming Language :: Rust
Classifier: Intended Audience :: Developers
Classifier: Development Status :: 4 - Beta
Classifier: Topic :: System :: Networking
Classifier: License :: OSI Approved :: Apache Software License
Classifier: License :: OSI Approved :: MIT License
Classifier: Operating System :: POSIX :: Linux
Classifier: Operating System :: POSIX :: BSD :: FreeBSD
Classifier: Operating System :: MacOS :: MacOS X
Classifier: Operating System :: Microsoft :: Windows
Requires-Dist: pytest ; extra == 'test'
Provides-Extra: test
Summary: Lock-Free Zero-Copy Inter-process Communication
Keywords: ipc,inter-process communication,zero-copy,shared memory,publish-subscribe,request-response,event
Home-Page: https://iceoryx.io
Author: Contributors of eclipse-iceoryx
License-Expression: Apache-2.0 OR MIT
Requires-Python: >=3.10, <4.0
Project-URL: changelog, https://github.com/eclipse-iceoryx/iceoryx2/blob/main/CHANGELOG.md
Project-URL: documentation, https://ekxide.github.io/iceoryx2-book
Project-URL: homepage, https://iceoryx.io
Project-URL: repository, https://github.com/eclipse-iceoryx/iceoryx2
